jambottle/__init__.py
jambottle/__main__.py
jambottle/jambottle.py
jambottle-1.0.0.dist-info/LICENSE
jambottle-1.0.0.dist-info/METADATA
jambottle-1.0.0.dist-info/WHEEL
jambottle-1.0.0.dist-info/entry_points.txt
jambottle-1.0.0.dist-info/top_level.txt
jambottle-1.0.0.dist-info/zip-safe
jambottle-1.0.0.dist-info/RECORD
