Metadata-Version: 2.1
Name: jambottle
Version: 1.0.0
Summary: A bot that announces new itch.io jam entries to a discord channel
Home-page: UNKNOWN
Author: Natalie Fearnley
Author-email: nfearnley@gmail.com
License: MIT
Project-URL: Source, https://github.com/nfearnley/jambottle
Project-URL: Tracker, https://github.com/nfearnley/jambottle/issues
Keywords: game,space,simulator
Platform: unix
Platform: linux
Platform: osx
Platform: cygwin
Platform: win32
Classifier: License :: OSI Approved :: MIT License
Classifier: Operating System :: OS Independent
Classifier: Programming Language :: Python :: 3.8
Classifier: Topic :: Communications :: Chat
Classifier: Topic :: Games/Entertainment
Classifier: Topic :: Software Development
Requires-Python: >=3.8
Requires-Dist: appdirs (==1.4.4)
Requires-Dist: arrow (==0.17.0)
Requires-Dist: discord.py (==1.5.1)
Requires-Dist: requests (==2.24.0)
Provides-Extra: dev
Requires-Dist: autopep8 (==1.5.4) ; extra == 'dev'
Requires-Dist: flake8 (==3.8.4) ; extra == 'dev'
